LICENSE
MANIFEST.in
README.md
setup.py
hxwacoyztm/__init__.py
hxwacoyztm/api_helper.py
hxwacoyztm/configuration.py
hxwacoyztm/decorators.py
hxwacoyztm/hxwacoyztm_client.py
hxwacoyztm.egg-info/PKG-INFO
hxwacoyztm.egg-info/SOURCES.txt
hxwacoyztm.egg-info/dependency_links.txt
hxwacoyztm.egg-info/requires.txt
hxwacoyztm.egg-info/top_level.txt
hxwacoyztm/controllers/__init__.py
hxwacoyztm/controllers/api_controller.py
hxwacoyztm/controllers/base_controller.py
hxwacoyztm/exceptions/__init__.py
hxwacoyztm/exceptions/api_exception.py
hxwacoyztm/http/__init__.py
hxwacoyztm/http/http_call_back.py
hxwacoyztm/http/http_client.py
hxwacoyztm/http/http_context.py
hxwacoyztm/http/http_method_enum.py
hxwacoyztm/http/http_request.py
hxwacoyztm/http/http_response.py
hxwacoyztm/http/requests_client.py
hxwacoyztm/http/auth/__init__.py
hxwacoyztm/http/auth/basic_auth.py
hxwacoyztm/models/__init__.py
hxwacoyztm/models/suite_code_enum.py
tests/__init__.py
tests/http_response_catcher.py
tests/test_helper.py
tests/controllers/__init__.py
tests/controllers/controller_test_base.py
tests/controllers/test_api_controller.py